dict2uml/__init__.py
dict2uml/dict2svg.py
dict2uml/dict2uml.py
dict2uml-1.0.dist-info/DESCRIPTION.rst
dict2uml-1.0.dist-info/entry_points.txt
dict2uml-1.0.dist-info/METADATA
dict2uml-1.0.dist-info/metadata.json
dict2uml-1.0.dist-info/RECORD
dict2uml-1.0.dist-info/top_level.txt
dict2uml-1.0.dist-info/WHEEL
